sizeforemir/__init__.py
sizeforemir/formula.py
sizeforemir-0.1.0.dist-info/LICENSE
sizeforemir-0.1.0.dist-info/METADATA
sizeforemir-0.1.0.dist-info/WHEEL
sizeforemir-0.1.0.dist-info/top_level.txt
sizeforemir-0.1.0.dist-info/RECORD
