Metadata-Version: 2.2
Name: sizeforemir
Version: 0.1.0
Summary: Boy ve ayak uzunluğuna göre özel hesaplama yapan bir kütüphane.
Author: Emir
License: MIT
Classifier: Programming Language :: Python :: 3
Classifier: License :: OSI Approved :: MIT License
Classifier: Operating System :: OS Independent
Requires-Python: >=3.6
License-File: LICENSE
Dynamic: author
Dynamic: classifier
Dynamic: requires-python
Dynamic: summary
